simplegeoip2.py
simplegeoip2-1.0.2.dist-info/DESCRIPTION.rst
simplegeoip2-1.0.2.dist-info/METADATA
simplegeoip2-1.0.2.dist-info/RECORD
simplegeoip2-1.0.2.dist-info/WHEEL
simplegeoip2-1.0.2.dist-info/entry_points.txt
simplegeoip2-1.0.2.dist-info/metadata.json
simplegeoip2-1.0.2.dist-info/top_level.txt
