Metadata-Version: 2.0
Name: simplegeoip2
Version: 1.0.2
Summary: A Python module and CLI tool that returns IP address ownership and location information based on MaxMind's Geolite2 databases
Home-page: https://github.com/seanthegeek/simplegeoip2
Author: Sean Whalen
Author-email: whalenster@gmail.com
License: Apache 2.0
Keywords: GeoIP,GeoLite2,MaxMind
Platform: UNKNOWN
Classifier: Development Status :: 5 - Production/Stable
Classifier: Intended Audience :: Developers
Classifier: Intended Audience :: Information Technology
Classifier: Operating System :: OS Independent
Classifier: License :: OSI Approved :: Apache Software License
Classifier: Programming Language :: Python :: 2
Classifier: Programming Language :: Python :: 2.7
Classifier: Programming Language :: Python :: 3
Classifier: Programming Language :: Python :: 3.3
Classifier: Programming Language :: Python :: 3.4
Classifier: Programming Language :: Python :: 3.5
Classifier: Programming Language :: Python :: 3.6
Requires-Dist: geoip2
